lxp/modules/lxp/__init__.py
lxp/modules/lxp/lxp.py
lxp-0.0.3.dist-info/METADATA
lxp-0.0.3.dist-info/WHEEL
lxp-0.0.3.dist-info/top_level.txt
lxp-0.0.3.dist-info/RECORD
