Metadata-Version: 2.1
Name: lxp
Version: 0.0.3
Summary: libraries for makeblock electronic platform
Home-page: https://makeblock.com
Author: makeblock
Author-email: 1282856796@qq.com
Requires-Dist: makeblock
